markpub/__init__.py
markpub/markpub.py
markpub/mistletoe_renderer/__init.py__
markpub/mistletoe_renderer/massivewiki.py
markpub/mistletoe_renderer/render.py
markpub/mistletoe_renderer/test.py
markpub/templates/Sidebar.md
markpub/templates/build-index.js
markpub/templates/gitignore-template.txt
markpub/templates/markpub-template.yaml
markpub/templates/netlify.toml
markpub/templates/package-lock.json
markpub/templates/package.json
markpub/templates/requirements.txt
markpub/templates/dot-github/dependabot.yml
markpub/templates/dot-github/workflows/gh-pages.yml
markpub-2.1.1.dist-info/METADATA
markpub-2.1.1.dist-info/WHEEL
markpub-2.1.1.dist-info/entry_points.txt
markpub-2.1.1.dist-info/licenses/LICENSE
markpub-2.1.1.dist-info/RECORD
