Metadata-Version: 2.4
Name: markpub
Version: 2.1.1
Summary: Build (web publish) Markdown and Massive Wiki sites.
Project-URL: homepage, https://markpub.org
Project-URL: repository, https://github.com/MarkPub/markpub
Author-email: Bill Anderson <band@acm.org>, Peter Kaminski <kaminski@istori.com>
License-Expression: MIT
License-File: LICENSE
Keywords: markdown,static-site-generator,wiki
Classifier: Development Status :: 5 - Production/Stable
Classifier: Intended Audience :: Developers
Classifier: License :: OSI Approved :: MIT License
Classifier: Programming Language :: Python :: 3.12
Requires-Python: <4.0,>=3.12
Requires-Dist: jinja2>=3.1.6
Requires-Dist: markpub-themes>=1.0.1
Requires-Dist: markupsafe>=3.0.2
Requires-Dist: mistletoe>=1.4.0
Requires-Dist: python-dateutil>=2.9.0.post0
Requires-Dist: pyyaml>=6.0.2
Requires-Dist: six>=1.17.0
